README.rst
setup.py
devel_tools.egg-info/PKG-INFO
devel_tools.egg-info/SOURCES.txt
devel_tools.egg-info/dependency_links.txt
devel_tools.egg-info/entry_points.txt
devel_tools.egg-info/not-zip-safe
devel_tools.egg-info/requires.txt
devel_tools.egg-info/top_level.txt
wok_code/__init__.py
wok_code/__main__.py
wok_code/conf.py
wok_code/cvt_csv_2_rst.py
wok_code/cvt_csv_2_xml.py
wok_code/cvt_csv_coa.py
wok_code/cvt_script
wok_code/eval_gtin.py
wok_code/gen_addons_table.py
wok_code/gen_readme.py
wok_code/license_mgnt.py
wok_code/makepo_it.py
wok_code/odoo_dependencies.py
wok_code/odoo_translation.py
wok_code/please
wok_code/please.py
wok_code/pull_from_oca.py
wok_code/to_pep8.py
wok_code/wget_odoo_repositories.py
wok_code/scripts/__init__.py
wok_code/scripts/main.py
wok_code/scripts/setup.info