Metadata-Version: 1.2
Name: devel-tools
Version: 1.0.2.5
Summary: Python developers tools
Home-page: https://zeroincombenze-tools.readthedocs.io
Author: Antonio Maria Vigliotti
Author-email: antoniomaria.vigliotti@gmail.com
License: Affero GPL
Project-URL: Source, https://github.com/zeroincombenze/tools
Project-URL: Documentation, https://zeroincombenze-tools.readthedocs.io
Keywords: linux travis development
Platform: UNKNOWN
Classifier: Development Status :: 4 - Beta
Classifier: License :: OSI Approved :: GNU Affero General Public License v3
Classifier: Operating System :: POSIX
Classifier: Programming Language :: Python :: 2.7
Classifier: Programming Language :: Python :: 3.6
Classifier: Programming Language :: Python :: 3.7
Classifier: Intended Audience :: Developers
Classifier: Topic :: Software Development
Classifier: Topic :: Software Development :: Build Tools
Classifier: Operating System :: OS Independent
